LICENSE
README.md
hive_archeology.py
setup.py
hive_archeology_bot.egg-info/PKG-INFO
hive_archeology_bot.egg-info/SOURCES.txt
hive_archeology_bot.egg-info/dependency_links.txt
hive_archeology_bot.egg-info/entry_points.txt
hive_archeology_bot.egg-info/not-zip-safe
hive_archeology_bot.egg-info/requires.txt
hive_archeology_bot.egg-info/top_level.txt